{
  "bitcoin": [
    {
      "timestamp": "2025-10-04T17:14:11.938450",
      "price": 121838,
      "change_24h": -0.9464325965895862
    },
    {
      "timestamp": "2025-10-04T17:29:13.678950",
      "price": 121900,
      "change_24h": -0.5669726347963221
    },
    {
      "timestamp": "2025-10-04T17:41:53.076618",
      "price": 121801,
      "change_24h": -0.6560646442581592
    },
    {
      "timestamp": "2025-10-04T17:54:42.084457",
      "price": 121741,
      "change_24h": -0.23026474998565089
    },
    {
      "timestamp": "2025-10-04T18:29:07.549093",
      "price": 121780,
      "change_24h": -0.6478458096598686
    },
    {
      "timestamp": "2025-10-04T18:46:20.430148",
      "price": 121711,
      "change_24h": -0.7857861726807225
    },
    {
      "timestamp": "2025-10-04T18:59:25.744884",
      "price": 121579,
      "change_24h": -0.8308849772928754
    },
    {
      "timestamp": "2025-10-04T19:18:36.236763",
      "price": 121818,
      "change_24h": -0.721950057738777
    },
    {
      "timestamp": "2025-10-04T19:31:59.324720",
      "price": 121870,
      "change_24h": -0.8612967783613195
    },
    {
      "timestamp": "2025-10-04T19:44:44.812524",
      "price": 121943,
      "change_24h": -0.6669207017365394
    }
  ],
  "cardano": [
    {
      "timestamp": "2025-10-04T17:14:11.938450",
      "price": 0.838681,
      "change_24h": -3.4816948619864942
    },
    {
      "timestamp": "2025-10-04T17:29:13.678950",
      "price": 0.838368,
      "change_24h": -3.4313184712343627
    },
    {
      "timestamp": "2025-10-04T17:41:53.076618",
      "price": 0.837009,
      "change_24h": -3.8628436671720485
    },
    {
      "timestamp": "2025-10-04T17:54:42.084457",
      "price": 0.835385,
      "change_24h": -3.366749322382381
    },
    {
      "timestamp": "2025-10-04T18:29:07.549093",
      "price": 0.836872,
      "change_24h": -3.693908424240437
    },
    {
      "timestamp": "2025-10-04T18:46:20.430148",
      "price": 0.836603,
      "change_24h": -3.903434932634553
    },
    {
      "timestamp": "2025-10-04T18:59:25.744884",
      "price": 0.836123,
      "change_24h": -3.9873882508990732
    },
    {
      "timestamp": "2025-10-04T19:18:36.236763",
      "price": 0.837837,
      "change_24h": -4.132384777990114
    },
    {
      "timestamp": "2025-10-04T19:31:59.324720",
      "price": 0.838439,
      "change_24h": -4.244017384429427
    },
    {
      "timestamp": "2025-10-04T19:44:44.812524",
      "price": 0.837113,
      "change_24h": -4.323307596306094
    }
  ],
  "ethereum": [
    {
      "timestamp": "2025-10-04T17:14:11.938450",
      "price": 4471.32,
      "change_24h": -1.0867266058594849
    },
    {
      "timestamp": "2025-10-04T17:29:13.678950",
      "price": 4473.18,
      "change_24h": -0.690137495901771
    },
    {
      "timestamp": "2025-10-04T17:41:53.076618",
      "price": 4463.78,
      "change_24h": -1.1162949610936672
    },
    {
      "timestamp": "2025-10-04T17:54:42.084457",
      "price": 4459.2,
      "change_24h": -0.5289086805207096
    },
    {
      "timestamp": "2025-10-04T18:29:07.549093",
      "price": 4461.11,
      "change_24h": -0.956161710081239
    },
    {
      "timestamp": "2025-10-04T18:46:20.430148",
      "price": 4455.69,
      "change_24h": -1.071672781104429
    },
    {
      "timestamp": "2025-10-04T18:59:25.744884",
      "price": 4453.38,
      "change_24h": -1.3391136393780692
    },
    {
      "timestamp": "2025-10-04T19:18:36.236763",
      "price": 4462.2,
      "change_24h": -1.4942997846184665
    },
    {
      "timestamp": "2025-10-04T19:31:59.324720",
      "price": 4466.88,
      "change_24h": -1.4986407609363785
    },
    {
      "timestamp": "2025-10-04T19:44:44.812524",
      "price": 4467.49,
      "change_24h": -1.293162333863891
    }
  ],
  "litecoin": [
    {
      "timestamp": "2025-10-04T17:14:11.938450",
      "price": 118.52,
      "change_24h": -1.2864475193645584
    },
    {
      "timestamp": "2025-10-04T17:29:13.678950",
      "price": 118.46,
      "change_24h": -2.504157999455269
    },
    {
      "timestamp": "2025-10-04T17:41:53.076618",
      "price": 118.32,
      "change_24h": -3.6145276128539106
    },
    {
      "timestamp": "2025-10-04T17:54:42.084457",
      "price": 118.2,
      "change_24h": -3.8353979927807624
    },
    {
      "timestamp": "2025-10-04T18:29:07.549093",
      "price": 118.48,
      "change_24h": -3.4898539576386147
    },
    {
      "timestamp": "2025-10-04T18:46:20.430148",
      "price": 118.61,
      "change_24h": -3.3958690536638185
    },
    {
      "timestamp": "2025-10-04T18:59:25.744884",
      "price": 118.55,
      "change_24h": -4.134767734013905
    },
    {
      "timestamp": "2025-10-04T19:18:36.236763",
      "price": 119.17,
      "change_24h": -3.331020330396823
    },
    {
      "timestamp": "2025-10-04T19:31:59.324720",
      "price": 119.11,
      "change_24h": -2.965921298011989
    },
    {
      "timestamp": "2025-10-04T19:44:44.812524",
      "price": 119.02,
      "change_24h": -3.3776027405856954
    }
  ],
  "solana": [
    {
      "timestamp": "2025-10-04T17:14:11.938450",
      "price": 226.44,
      "change_24h": -2.5267248838171725
    },
    {
      "timestamp": "2025-10-04T17:29:13.678950",
      "price": 226.54,
      "change_24h": -2.464331334000193
    },
    {
      "timestamp": "2025-10-04T17:41:53.076618",
      "price": 226.67,
      "change_24h": -2.476358762274604
    },
    {
      "timestamp": "2025-10-04T17:54:42.084457",
      "price": 226.31,
      "change_24h": -1.805789124157469
    },
    {
      "timestamp": "2025-10-04T18:29:07.549093",
      "price": 226.77,
      "change_24h": -2.7294895457651784
    },
    {
      "timestamp": "2025-10-04T18:46:20.430148",
      "price": 226.33,
      "change_24h": -2.814367452663154
    },
    {
      "timestamp": "2025-10-04T18:59:25.744884",
      "price": 226.09,
      "change_24h": -3.04086215382574
    },
    {
      "timestamp": "2025-10-04T19:18:36.236763",
      "price": 226.36,
      "change_24h": -3.304619253096646
    },
    {
      "timestamp": "2025-10-04T19:31:59.324720",
      "price": 226.6,
      "change_24h": -3.42552534905663
    },
    {
      "timestamp": "2025-10-04T19:44:44.812524",
      "price": 226.69,
      "change_24h": -3.516685097580373
    }
  ]
}