{
  "bitcoin": [
    {
      "timestamp": "2025-08-15T08:37:26.745062",
      "price": 119199,
      "change_24h": -2.156142290844618
    },
    {
      "timestamp": "2025-08-15T08:56:31.130979",
      "price": 119049,
      "change_24h": -2.166484154572678
    },
    {
      "timestamp": "2025-08-15T09:29:33.363885",
      "price": 118816,
      "change_24h": -2.504407101047042
    },
    {
      "timestamp": "2025-08-15T09:46:54.590627",
      "price": 118797,
      "change_24h": -2.349481305786673
    },
    {
      "timestamp": "2025-08-15T09:59:40.400831",
      "price": 118741,
      "change_24h": -2.3604028235799044
    },
    {
      "timestamp": "2025-08-15T10:32:30.795281",
      "price": 119019,
      "change_24h": -2.1523782387616914
    },
    {
      "timestamp": "2025-08-15T10:50:10.336982",
      "price": 119009,
      "change_24h": -1.8428747284270248
    },
    {
      "timestamp": "2025-08-15T11:12:07.458238",
      "price": 119096,
      "change_24h": -1.4784100597734753
    },
    {
      "timestamp": "2025-08-15T11:30:31.562489",
      "price": 119090,
      "change_24h": -1.4432201104648066
    },
    {
      "timestamp": "2025-08-15T11:44:24.533897",
      "price": 119145,
      "change_24h": -1.4141402403771477
    }
  ],
  "cardano": [
    {
      "timestamp": "2025-08-15T08:37:26.745062",
      "price": 0.950977,
      "change_24h": -3.5479660647130573
    },
    {
      "timestamp": "2025-08-15T08:56:31.130979",
      "price": 0.95031,
      "change_24h": -3.6947726602035353
    },
    {
      "timestamp": "2025-08-15T09:29:33.363885",
      "price": 0.943673,
      "change_24h": -4.624759137069469
    },
    {
      "timestamp": "2025-08-15T09:46:54.590627",
      "price": 0.943895,
      "change_24h": -4.703743340973935
    },
    {
      "timestamp": "2025-08-15T09:59:40.400831",
      "price": 0.945057,
      "change_24h": -4.757305116525159
    },
    {
      "timestamp": "2025-08-15T10:32:30.795281",
      "price": 0.956706,
      "change_24h": -2.858274662467359
    },
    {
      "timestamp": "2025-08-15T10:50:10.336982",
      "price": 0.951205,
      "change_24h": -2.1876029921509357
    },
    {
      "timestamp": "2025-08-15T11:12:07.458238",
      "price": 0.946079,
      "change_24h": -2.0397092657904636
    },
    {
      "timestamp": "2025-08-15T11:30:31.562489",
      "price": 0.944104,
      "change_24h": -2.323584687747785
    },
    {
      "timestamp": "2025-08-15T11:44:24.533897",
      "price": 0.944278,
      "change_24h": -2.3346920232052812
    }
  ],
  "ethereum": [
    {
      "timestamp": "2025-08-15T08:37:26.745062",
      "price": 4661.71,
      "change_24h": -1.4618542090795792
    },
    {
      "timestamp": "2025-08-15T08:56:31.130979",
      "price": 4645.55,
      "change_24h": -1.9014405634240326
    },
    {
      "timestamp": "2025-08-15T09:29:33.363885",
      "price": 4634.01,
      "change_24h": -2.396963291514149
    },
    {
      "timestamp": "2025-08-15T09:46:54.590627",
      "price": 4633.03,
      "change_24h": -2.691620979124915
    },
    {
      "timestamp": "2025-08-15T09:59:40.400831",
      "price": 4622.16,
      "change_24h": -2.8353606795362305
    },
    {
      "timestamp": "2025-08-15T10:32:30.795281",
      "price": 4641.39,
      "change_24h": -2.350171275172266
    },
    {
      "timestamp": "2025-08-15T10:50:10.336982",
      "price": 4645.33,
      "change_24h": -1.145610284357343
    },
    {
      "timestamp": "2025-08-15T11:12:07.458238",
      "price": 4643.15,
      "change_24h": -1.4239146025376512
    },
    {
      "timestamp": "2025-08-15T11:30:31.562489",
      "price": 4631.15,
      "change_24h": -1.5407855102032688
    },
    {
      "timestamp": "2025-08-15T11:44:24.533897",
      "price": 4639.92,
      "change_24h": -1.498647580408146
    }
  ],
  "litecoin": [
    {
      "timestamp": "2025-08-15T08:37:26.745062",
      "price": 121.61,
      "change_24h": -5.443521794510101
    },
    {
      "timestamp": "2025-08-15T08:56:31.130979",
      "price": 121.46,
      "change_24h": -5.210785939104209
    },
    {
      "timestamp": "2025-08-15T09:29:33.363885",
      "price": 121.03,
      "change_24h": -5.725939980489255
    },
    {
      "timestamp": "2025-08-15T09:46:54.590627",
      "price": 121.09,
      "change_24h": -5.786026899737185
    },
    {
      "timestamp": "2025-08-15T09:59:40.400831",
      "price": 120.94,
      "change_24h": -6.195818168272233
    },
    {
      "timestamp": "2025-08-15T10:32:30.795281",
      "price": 121.17,
      "change_24h": -5.7145754934477235
    },
    {
      "timestamp": "2025-08-15T10:50:10.336982",
      "price": 121.03,
      "change_24h": -5.3124605771791895
    },
    {
      "timestamp": "2025-08-15T11:12:07.458238",
      "price": 120.88,
      "change_24h": -5.333367332751957
    },
    {
      "timestamp": "2025-08-15T11:30:31.562489",
      "price": 120.52,
      "change_24h": -5.818749210804275
    },
    {
      "timestamp": "2025-08-15T11:44:24.533897",
      "price": 120.76,
      "change_24h": -5.630789333653271
    }
  ],
  "solana": [
    {
      "timestamp": "2025-08-15T08:37:26.745062",
      "price": 197.19,
      "change_24h": -3.2314407454938756
    },
    {
      "timestamp": "2025-08-15T08:56:31.130979",
      "price": 196.94,
      "change_24h": -3.033545110087091
    },
    {
      "timestamp": "2025-08-15T09:29:33.363885",
      "price": 195.92,
      "change_24h": -4.393770765726547
    },
    {
      "timestamp": "2025-08-15T09:46:54.590627",
      "price": 195.32,
      "change_24h": -4.6286512923330285
    },
    {
      "timestamp": "2025-08-15T09:59:40.400831",
      "price": 194.62,
      "change_24h": -5.228884365868339
    },
    {
      "timestamp": "2025-08-15T10:32:30.795281",
      "price": 195.61,
      "change_24h": -4.371810498101493
    },
    {
      "timestamp": "2025-08-15T10:50:10.336982",
      "price": 195.38,
      "change_24h": -3.7558288153189423
    },
    {
      "timestamp": "2025-08-15T11:12:07.458238",
      "price": 195.13,
      "change_24h": -3.6665235256443705
    },
    {
      "timestamp": "2025-08-15T11:30:31.562489",
      "price": 194.24,
      "change_24h": -4.275219297914594
    },
    {
      "timestamp": "2025-08-15T11:44:24.533897",
      "price": 194.5,
      "change_24h": -4.4123825758175546
    }
  ]
}