{
  "bitcoin": [
    {
      "timestamp": "2025-11-29T09:57:55.047663",
      "price": 90588,
      "change_24h": -1.0813817491400237
    },
    {
      "timestamp": "2025-11-29T10:29:23.922564",
      "price": 90614,
      "change_24h": -1.0573699042054887
    },
    {
      "timestamp": "2025-11-29T10:45:45.459898",
      "price": 90624,
      "change_24h": -1.0880021442575858
    },
    {
      "timestamp": "2025-11-29T10:58:53.333505",
      "price": 90597,
      "change_24h": -1.3402434969424628
    },
    {
      "timestamp": "2025-11-29T11:22:44.467305",
      "price": 90567,
      "change_24h": -0.6971739860945988
    },
    {
      "timestamp": "2025-11-29T11:37:03.862726",
      "price": 90548,
      "change_24h": -0.8090397814737489
    },
    {
      "timestamp": "2025-11-29T11:50:08.701521",
      "price": 90623,
      "change_24h": -0.8251888489054645
    },
    {
      "timestamp": "2025-11-29T12:25:37.033547",
      "price": 90594,
      "change_24h": -1.040175109852322
    },
    {
      "timestamp": "2025-11-29T13:04:31.684028",
      "price": 90659,
      "change_24h": -0.9781471434799821
    },
    {
      "timestamp": "2025-11-29T13:34:48.321024",
      "price": 90769,
      "change_24h": -0.8245664845433018
    }
  ],
  "cardano": [
    {
      "timestamp": "2025-11-29T09:57:55.047663",
      "price": 0.414992,
      "change_24h": -4.082967404884172
    },
    {
      "timestamp": "2025-11-29T10:29:23.922564",
      "price": 0.416204,
      "change_24h": -3.4260199776349447
    },
    {
      "timestamp": "2025-11-29T10:45:45.459898",
      "price": 0.41711,
      "change_24h": -3.398313099634711
    },
    {
      "timestamp": "2025-11-29T10:58:53.333505",
      "price": 0.417526,
      "change_24h": -3.262771696732552
    },
    {
      "timestamp": "2025-11-29T11:22:44.467305",
      "price": 0.417214,
      "change_24h": -1.9522034900015166
    },
    {
      "timestamp": "2025-11-29T11:37:03.862726",
      "price": 0.417065,
      "change_24h": -1.9868004080765884
    },
    {
      "timestamp": "2025-11-29T11:50:08.701521",
      "price": 0.41848,
      "change_24h": -1.754772913792492
    },
    {
      "timestamp": "2025-11-29T12:25:37.033547",
      "price": 0.417983,
      "change_24h": -1.81454593133669
    },
    {
      "timestamp": "2025-11-29T13:04:31.684028",
      "price": 0.418143,
      "change_24h": -1.4496920736806556
    },
    {
      "timestamp": "2025-11-29T13:34:48.321024",
      "price": 0.417785,
      "change_24h": -1.912069643497598
    }
  ],
  "ethereum": [
    {
      "timestamp": "2025-11-29T09:57:55.047663",
      "price": 3003.36,
      "change_24h": -1.666097472894978
    },
    {
      "timestamp": "2025-11-29T10:29:23.922564",
      "price": 3004.22,
      "change_24h": -1.6047014558232024
    },
    {
      "timestamp": "2025-11-29T10:45:45.459898",
      "price": 3003.64,
      "change_24h": -1.5871635153452377
    },
    {
      "timestamp": "2025-11-29T10:58:53.333505",
      "price": 2999.19,
      "change_24h": -1.9963206496617771
    },
    {
      "timestamp": "2025-11-29T11:22:44.467305",
      "price": 2995.81,
      "change_24h": -1.0194342068406355
    },
    {
      "timestamp": "2025-11-29T11:37:03.862726",
      "price": 2999.22,
      "change_24h": -1.0239126996670143
    },
    {
      "timestamp": "2025-11-29T11:50:08.701521",
      "price": 3001.2,
      "change_24h": -0.964430304587884
    },
    {
      "timestamp": "2025-11-29T12:25:37.033547",
      "price": 2994.15,
      "change_24h": -1.4975587555102587
    },
    {
      "timestamp": "2025-11-29T13:04:31.684028",
      "price": 2997.48,
      "change_24h": -1.2338937782722978
    },
    {
      "timestamp": "2025-11-29T13:34:48.321024",
      "price": 3001.22,
      "change_24h": -1.1716789569128363
    }
  ],
  "litecoin": [
    {
      "timestamp": "2025-11-29T09:57:55.047663",
      "price": 84.41,
      "change_24h": -1.4805969294269914
    },
    {
      "timestamp": "2025-11-29T10:29:23.922564",
      "price": 84.43,
      "change_24h": -1.2948966897018688
    },
    {
      "timestamp": "2025-11-29T10:45:45.459898",
      "price": 84.53,
      "change_24h": -1.263003329556574
    },
    {
      "timestamp": "2025-11-29T10:58:53.333505",
      "price": 84.61,
      "change_24h": -1.3013162154196636
    },
    {
      "timestamp": "2025-11-29T11:22:44.467305",
      "price": 84.45,
      "change_24h": -0.6482672334800548
    },
    {
      "timestamp": "2025-11-29T11:37:03.862726",
      "price": 84.4,
      "change_24h": -0.5742327604741171
    },
    {
      "timestamp": "2025-11-29T11:50:08.701521",
      "price": 84.59,
      "change_24h": -0.3782939870874918
    },
    {
      "timestamp": "2025-11-29T12:25:37.033547",
      "price": 84.32,
      "change_24h": -0.8755957833445743
    },
    {
      "timestamp": "2025-11-29T13:04:31.684028",
      "price": 84.2,
      "change_24h": -0.9823238401104436
    },
    {
      "timestamp": "2025-11-29T13:34:48.321024",
      "price": 84.18,
      "change_24h": -1.0842221747525167
    }
  ],
  "solana": [
    {
      "timestamp": "2025-11-29T09:57:55.047663",
      "price": 136.7,
      "change_24h": -3.504935068406582
    },
    {
      "timestamp": "2025-11-29T10:29:23.922564",
      "price": 136.85,
      "change_24h": -3.598630374621602
    },
    {
      "timestamp": "2025-11-29T10:45:45.459898",
      "price": 136.92,
      "change_24h": -3.5029835653321064
    },
    {
      "timestamp": "2025-11-29T10:58:53.333505",
      "price": 136.95,
      "change_24h": -3.6045591082955784
    },
    {
      "timestamp": "2025-11-29T11:22:44.467305",
      "price": 136.9,
      "change_24h": -2.513679069559173
    },
    {
      "timestamp": "2025-11-29T11:37:03.862726",
      "price": 137.04,
      "change_24h": -2.4748887081646833
    },
    {
      "timestamp": "2025-11-29T11:50:08.701521",
      "price": 137.31,
      "change_24h": -2.4191826633800577
    },
    {
      "timestamp": "2025-11-29T12:25:37.033547",
      "price": 137.06,
      "change_24h": -2.872639386255889
    },
    {
      "timestamp": "2025-11-29T13:04:31.684028",
      "price": 136.98,
      "change_24h": -2.712859994692806
    },
    {
      "timestamp": "2025-11-29T13:34:48.321024",
      "price": 136.93,
      "change_24h": -2.92361919327614
    }
  ]
}