{
  "bitcoin": [
    {
      "timestamp": "2026-01-26T15:15:43.204288",
      "price": 88635,
      "change_24h": 0.03132167025655944
    },
    {
      "timestamp": "2026-01-26T15:47:54.378314",
      "price": 87308,
      "change_24h": -1.3981336883499054
    },
    {
      "timestamp": "2026-01-26T16:17:33.229261",
      "price": 87180,
      "change_24h": -0.5183972804689834
    },
    {
      "timestamp": "2026-01-26T16:56:45.499532",
      "price": 87672,
      "change_24h": -0.2939962901017599
    },
    {
      "timestamp": "2026-01-26T17:38:38.208142",
      "price": 87350,
      "change_24h": -0.49498226024682856
    },
    {
      "timestamp": "2026-01-26T17:58:24.875966",
      "price": 87640,
      "change_24h": -0.1726801332680816
    },
    {
      "timestamp": "2026-01-26T18:51:20.225223",
      "price": 88018,
      "change_24h": 1.0490719711628171
    },
    {
      "timestamp": "2026-01-26T19:20:42.985052",
      "price": 88223,
      "change_24h": 1.441064991690066
    },
    {
      "timestamp": "2026-01-26T19:42:50.671292",
      "price": 88232,
      "change_24h": 1.8366447003777469
    },
    {
      "timestamp": "2026-01-26T19:57:02.742652",
      "price": 87919,
      "change_24h": 1.7633705491166904
    }
  ],
  "cardano": [
    {
      "timestamp": "2026-01-26T15:15:43.204288",
      "price": 0.355688,
      "change_24h": 0.997318106423516
    },
    {
      "timestamp": "2026-01-26T15:47:54.378314",
      "price": 0.351727,
      "change_24h": -0.25189764749712196
    },
    {
      "timestamp": "2026-01-26T16:17:33.229261",
      "price": 0.35192,
      "change_24h": 2.257837596593441
    },
    {
      "timestamp": "2026-01-26T16:56:45.499532",
      "price": 0.353352,
      "change_24h": 2.8553633256367843
    },
    {
      "timestamp": "2026-01-26T17:38:38.208142",
      "price": 0.351039,
      "change_24h": 2.6033789282320385
    },
    {
      "timestamp": "2026-01-26T17:58:24.875966",
      "price": 0.352526,
      "change_24h": 3.118983816057243
    },
    {
      "timestamp": "2026-01-26T18:51:20.225223",
      "price": 0.353501,
      "change_24h": 4.273319139573362
    },
    {
      "timestamp": "2026-01-26T19:20:42.985052",
      "price": 0.352987,
      "change_24h": 4.05471465212773
    },
    {
      "timestamp": "2026-01-26T19:42:50.671292",
      "price": 0.352839,
      "change_24h": 4.936446046144785
    },
    {
      "timestamp": "2026-01-26T19:57:02.742652",
      "price": 0.352192,
      "change_24h": 5.226360441957082
    }
  ],
  "ethereum": [
    {
      "timestamp": "2026-01-26T15:15:43.204288",
      "price": 2940.44,
      "change_24h": 0.3629368906261736
    },
    {
      "timestamp": "2026-01-26T15:47:54.378314",
      "price": 2887.95,
      "change_24h": -1.3363658802230032
    },
    {
      "timestamp": "2026-01-26T16:17:33.229261",
      "price": 2892.32,
      "change_24h": 0.2525008607818153
    },
    {
      "timestamp": "2026-01-26T16:56:45.499532",
      "price": 2906.5,
      "change_24h": 0.4401961622406317
    },
    {
      "timestamp": "2026-01-26T17:38:38.208142",
      "price": 2899.15,
      "change_24h": 0.5382681668302632
    },
    {
      "timestamp": "2026-01-26T17:58:24.875966",
      "price": 2909.57,
      "change_24h": 1.0216525201382103
    },
    {
      "timestamp": "2026-01-26T18:51:20.225223",
      "price": 2917.41,
      "change_24h": 2.816518534289007
    },
    {
      "timestamp": "2026-01-26T19:20:42.985052",
      "price": 2927.0,
      "change_24h": 3.375578818729166
    },
    {
      "timestamp": "2026-01-26T19:42:50.671292",
      "price": 2930.04,
      "change_24h": 3.6870550804677604
    },
    {
      "timestamp": "2026-01-26T19:57:02.742652",
      "price": 2920.16,
      "change_24h": 3.8005422168809604
    }
  ],
  "litecoin": [
    {
      "timestamp": "2026-01-26T15:15:43.204288",
      "price": 69.41,
      "change_24h": 0.551424106941371
    },
    {
      "timestamp": "2026-01-26T15:47:54.378314",
      "price": 68.84,
      "change_24h": -0.396315592987067
    },
    {
      "timestamp": "2026-01-26T16:17:33.229261",
      "price": 69.0,
      "change_24h": 0.24331530096093437
    },
    {
      "timestamp": "2026-01-26T16:56:45.499532",
      "price": 69.37,
      "change_24h": 1.8070655209597424
    },
    {
      "timestamp": "2026-01-26T17:38:38.208142",
      "price": 68.88,
      "change_24h": 2.0412979604375074
    },
    {
      "timestamp": "2026-01-26T17:58:24.875966",
      "price": 69.12,
      "change_24h": 2.1100471929362126
    },
    {
      "timestamp": "2026-01-26T18:51:20.225223",
      "price": 69.65,
      "change_24h": 4.087320442351958
    },
    {
      "timestamp": "2026-01-26T19:20:42.985052",
      "price": 69.28,
      "change_24h": 3.5485678647230823
    },
    {
      "timestamp": "2026-01-26T19:42:50.671292",
      "price": 69.15,
      "change_24h": 4.284745879935215
    },
    {
      "timestamp": "2026-01-26T19:57:02.742652",
      "price": 69.06,
      "change_24h": 4.572807196163447
    }
  ],
  "solana": [
    {
      "timestamp": "2026-01-26T15:15:43.204288",
      "price": 124.1,
      "change_24h": -1.4475070779707924
    },
    {
      "timestamp": "2026-01-26T15:47:54.378314",
      "price": 123.32,
      "change_24h": -1.962975069177454
    },
    {
      "timestamp": "2026-01-26T16:17:33.229261",
      "price": 123.52,
      "change_24h": 0.7973183286798968
    },
    {
      "timestamp": "2026-01-26T16:56:45.499532",
      "price": 124.36,
      "change_24h": 1.530017259690383
    },
    {
      "timestamp": "2026-01-26T17:38:38.208142",
      "price": 123.49,
      "change_24h": 1.2634588647627616
    },
    {
      "timestamp": "2026-01-26T17:58:24.875966",
      "price": 124.03,
      "change_24h": 1.4974671895904548
    },
    {
      "timestamp": "2026-01-26T18:51:20.225223",
      "price": 124.47,
      "change_24h": 2.8116273426994876
    },
    {
      "timestamp": "2026-01-26T19:20:42.985052",
      "price": 124.55,
      "change_24h": 2.8439631708399293
    },
    {
      "timestamp": "2026-01-26T19:42:50.671292",
      "price": 124.35,
      "change_24h": 3.78184461780335
    },
    {
      "timestamp": "2026-01-26T19:57:02.742652",
      "price": 124.28,
      "change_24h": 4.470412605582115
    }
  ]
}