{
  "bitcoin": [
    {
      "timestamp": "2025-11-10T08:54:57.052062",
      "price": 105961,
      "change_24h": 4.0044190390222605
    },
    {
      "timestamp": "2025-11-10T09:29:32.549145",
      "price": 106246,
      "change_24h": 4.212163024728558
    },
    {
      "timestamp": "2025-11-10T09:47:58.192196",
      "price": 106489,
      "change_24h": 4.547494266568379
    },
    {
      "timestamp": "2025-11-10T10:11:24.173066",
      "price": 106329,
      "change_24h": 4.690099616573551
    },
    {
      "timestamp": "2025-11-10T10:41:30.080135",
      "price": 106041,
      "change_24h": 4.378603464802081
    },
    {
      "timestamp": "2025-11-10T10:54:47.614667",
      "price": 106048,
      "change_24h": 4.116657328341489
    },
    {
      "timestamp": "2025-11-10T11:21:21.494073",
      "price": 106004,
      "change_24h": 3.7310534383465863
    },
    {
      "timestamp": "2025-11-10T11:37:41.170295",
      "price": 106146,
      "change_24h": 4.007477806429532
    },
    {
      "timestamp": "2025-11-10T11:50:48.773379",
      "price": 106246,
      "change_24h": 3.91614527032337
    },
    {
      "timestamp": "2025-11-10T12:31:34.285205",
      "price": 105903,
      "change_24h": 3.6779281663511325
    }
  ],
  "cardano": [
    {
      "timestamp": "2025-11-10T08:54:57.052062",
      "price": 0.585955,
      "change_24h": 4.761365671874052
    },
    {
      "timestamp": "2025-11-10T09:29:32.549145",
      "price": 0.591255,
      "change_24h": 5.5451606705894445
    },
    {
      "timestamp": "2025-11-10T09:47:58.192196",
      "price": 0.598604,
      "change_24h": 7.388703286347225
    },
    {
      "timestamp": "2025-11-10T10:11:24.173066",
      "price": 0.599709,
      "change_24h": 8.72304413158355
    },
    {
      "timestamp": "2025-11-10T10:41:30.080135",
      "price": 0.596159,
      "change_24h": 7.877266834265159
    },
    {
      "timestamp": "2025-11-10T10:54:47.614667",
      "price": 0.595914,
      "change_24h": 7.131282657050708
    },
    {
      "timestamp": "2025-11-10T11:21:21.494073",
      "price": 0.597827,
      "change_24h": 6.339992641068479
    },
    {
      "timestamp": "2025-11-10T11:37:41.170295",
      "price": 0.595073,
      "change_24h": 5.930143831791485
    },
    {
      "timestamp": "2025-11-10T11:50:48.773379",
      "price": 0.596039,
      "change_24h": 6.004640356064823
    },
    {
      "timestamp": "2025-11-10T12:31:34.285205",
      "price": 0.593205,
      "change_24h": 5.381364458579503
    }
  ],
  "ethereum": [
    {
      "timestamp": "2025-11-10T08:54:57.052062",
      "price": 3593.65,
      "change_24h": 5.210891628651832
    },
    {
      "timestamp": "2025-11-10T09:29:32.549145",
      "price": 3603.63,
      "change_24h": 5.326691733194561
    },
    {
      "timestamp": "2025-11-10T09:47:58.192196",
      "price": 3618.93,
      "change_24h": 6.015844120354473
    },
    {
      "timestamp": "2025-11-10T10:11:24.173066",
      "price": 3622.67,
      "change_24h": 6.8109688384169615
    },
    {
      "timestamp": "2025-11-10T10:41:30.080135",
      "price": 3607.18,
      "change_24h": 6.392713270259254
    },
    {
      "timestamp": "2025-11-10T10:54:47.614667",
      "price": 3606.28,
      "change_24h": 6.151880301579007
    },
    {
      "timestamp": "2025-11-10T11:21:21.494073",
      "price": 3606.25,
      "change_24h": 5.354156834463125
    },
    {
      "timestamp": "2025-11-10T11:37:41.170295",
      "price": 3609.25,
      "change_24h": 5.604418197705999
    },
    {
      "timestamp": "2025-11-10T11:50:48.773379",
      "price": 3616.66,
      "change_24h": 5.532636328282189
    },
    {
      "timestamp": "2025-11-10T12:31:34.285205",
      "price": 3591.07,
      "change_24h": 4.209647110797602
    }
  ],
  "litecoin": [
    {
      "timestamp": "2025-11-10T08:54:57.052062",
      "price": 107.13,
      "change_24h": 5.972554298086799
    },
    {
      "timestamp": "2025-11-10T09:29:32.549145",
      "price": 107.76,
      "change_24h": 6.481254927822036
    },
    {
      "timestamp": "2025-11-10T09:47:58.192196",
      "price": 107.98,
      "change_24h": 7.513192845363494
    },
    {
      "timestamp": "2025-11-10T10:11:24.173066",
      "price": 108.1,
      "change_24h": 8.605658643001178
    },
    {
      "timestamp": "2025-11-10T10:41:30.080135",
      "price": 107.14,
      "change_24h": 6.18412365938799
    },
    {
      "timestamp": "2025-11-10T10:54:47.614667",
      "price": 107.09,
      "change_24h": 3.327782569874461
    },
    {
      "timestamp": "2025-11-10T11:21:21.494073",
      "price": 107.42,
      "change_24h": 2.1777787744921895
    },
    {
      "timestamp": "2025-11-10T11:37:41.170295",
      "price": 107.39,
      "change_24h": 2.641032286216655
    },
    {
      "timestamp": "2025-11-10T11:50:48.773379",
      "price": 107.69,
      "change_24h": 2.998329234967571
    },
    {
      "timestamp": "2025-11-10T12:31:34.285205",
      "price": 106.52,
      "change_24h": 3.8620256255719916
    }
  ],
  "solana": [
    {
      "timestamp": "2025-11-10T08:54:57.052062",
      "price": 166.54,
      "change_24h": 4.665355018703109
    },
    {
      "timestamp": "2025-11-10T09:29:32.549145",
      "price": 167.35,
      "change_24h": 5.088500490222
    },
    {
      "timestamp": "2025-11-10T09:47:58.192196",
      "price": 168.87,
      "change_24h": 6.313578748585806
    },
    {
      "timestamp": "2025-11-10T10:11:24.173066",
      "price": 169.27,
      "change_24h": 7.18424322899554
    },
    {
      "timestamp": "2025-11-10T10:41:30.080135",
      "price": 168.25,
      "change_24h": 6.807998353706214
    },
    {
      "timestamp": "2025-11-10T10:54:47.614667",
      "price": 168.31,
      "change_24h": 6.560490448235506
    },
    {
      "timestamp": "2025-11-10T11:21:21.494073",
      "price": 168.29,
      "change_24h": 5.754142366531943
    },
    {
      "timestamp": "2025-11-10T11:37:41.170295",
      "price": 168.28,
      "change_24h": 5.933462693511119
    },
    {
      "timestamp": "2025-11-10T11:50:48.773379",
      "price": 168.52,
      "change_24h": 5.945011224999287
    },
    {
      "timestamp": "2025-11-10T12:31:34.285205",
      "price": 167.62,
      "change_24h": 5.29154693584227
    }
  ]
}