{
  "bitcoin": [
    {
      "timestamp": "2026-01-12T19:57:01.190312",
      "price": 91765,
      "change_24h": 1.2706783580449192
    },
    {
      "timestamp": "2026-01-12T20:34:26.323417",
      "price": 91484,
      "change_24h": 1.1270526618246375
    },
    {
      "timestamp": "2026-01-12T20:53:57.532508",
      "price": 91391,
      "change_24h": 0.9562716329311306
    },
    {
      "timestamp": "2026-01-12T21:25:04.952688",
      "price": 91321,
      "change_24h": 0.8362076231240334
    },
    {
      "timestamp": "2026-01-12T21:44:27.369961",
      "price": 91270,
      "change_24h": 0.7997196974941523
    },
    {
      "timestamp": "2026-01-12T21:57:25.838037",
      "price": 90921,
      "change_24h": 0.2934885412505289
    },
    {
      "timestamp": "2026-01-12T22:28:18.652387",
      "price": 91251,
      "change_24h": 0.7419780445582271
    },
    {
      "timestamp": "2026-01-12T22:47:02.487778",
      "price": 91230,
      "change_24h": 0.724638362819056
    },
    {
      "timestamp": "2026-01-12T23:00:03.300079",
      "price": 91165,
      "change_24h": 0.8033924245940436
    },
    {
      "timestamp": "2026-01-12T23:25:24.639829",
      "price": 91095,
      "change_24h": 0.3037079352286428
    }
  ],
  "cardano": [
    {
      "timestamp": "2026-01-12T19:57:01.190312",
      "price": 0.392604,
      "change_24h": 0.14070619862082206
    },
    {
      "timestamp": "2026-01-12T20:34:26.323417",
      "price": 0.391232,
      "change_24h": 0.9022530533955405
    },
    {
      "timestamp": "2026-01-12T20:53:57.532508",
      "price": 0.389205,
      "change_24h": 0.10153271960812646
    },
    {
      "timestamp": "2026-01-12T21:25:04.952688",
      "price": 0.387932,
      "change_24h": -0.14002452399653875
    },
    {
      "timestamp": "2026-01-12T21:44:27.369961",
      "price": 0.386585,
      "change_24h": -0.7486591164228893
    },
    {
      "timestamp": "2026-01-12T21:57:25.838037",
      "price": 0.384669,
      "change_24h": -1.7253394216347115
    },
    {
      "timestamp": "2026-01-12T22:28:18.652387",
      "price": 0.386447,
      "change_24h": -0.6035002823644586
    },
    {
      "timestamp": "2026-01-12T22:47:02.487778",
      "price": 0.38646,
      "change_24h": -0.5468152289249721
    },
    {
      "timestamp": "2026-01-12T23:00:03.300079",
      "price": 0.386654,
      "change_24h": -0.3276921313322819
    },
    {
      "timestamp": "2026-01-12T23:25:24.639829",
      "price": 0.38613,
      "change_24h": -1.0859164558145031
    }
  ],
  "ethereum": [
    {
      "timestamp": "2026-01-12T19:57:01.190312",
      "price": 3118.31,
      "change_24h": -0.05800043512600873
    },
    {
      "timestamp": "2026-01-12T20:34:26.323417",
      "price": 3103.89,
      "change_24h": -0.031755864689708174
    },
    {
      "timestamp": "2026-01-12T20:53:57.532508",
      "price": 3101.19,
      "change_24h": -0.24593370465306866
    },
    {
      "timestamp": "2026-01-12T21:25:04.952688",
      "price": 3098.02,
      "change_24h": -0.3552662950141544
    },
    {
      "timestamp": "2026-01-12T21:44:27.369961",
      "price": 3096.8,
      "change_24h": -0.43950509803557664
    },
    {
      "timestamp": "2026-01-12T21:57:25.838037",
      "price": 3086.79,
      "change_24h": -0.8217296105017665
    },
    {
      "timestamp": "2026-01-12T22:28:18.652387",
      "price": 3098.67,
      "change_24h": -0.40779534400119327
    },
    {
      "timestamp": "2026-01-12T22:47:02.487778",
      "price": 3098.59,
      "change_24h": -0.3887968362831418
    },
    {
      "timestamp": "2026-01-12T23:00:03.300079",
      "price": 3093.77,
      "change_24h": -0.36556423897013757
    },
    {
      "timestamp": "2026-01-12T23:25:24.639829",
      "price": 3089.52,
      "change_24h": -0.8545848149724687
    }
  ],
  "litecoin": [
    {
      "timestamp": "2026-01-12T19:57:01.190312",
      "price": 76.06,
      "change_24h": -5.241165668876537
    },
    {
      "timestamp": "2026-01-12T20:34:26.323417",
      "price": 76.15,
      "change_24h": -4.558331056079568
    },
    {
      "timestamp": "2026-01-12T20:53:57.532508",
      "price": 76.01,
      "change_24h": -4.892881443738087
    },
    {
      "timestamp": "2026-01-12T21:25:04.952688",
      "price": 76.32,
      "change_24h": -3.8126699701492144
    },
    {
      "timestamp": "2026-01-12T21:44:27.369961",
      "price": 76.36,
      "change_24h": -3.600912731535372
    },
    {
      "timestamp": "2026-01-12T21:57:25.838037",
      "price": 76.13,
      "change_24h": -3.877433757904041
    },
    {
      "timestamp": "2026-01-12T22:28:18.652387",
      "price": 76.52,
      "change_24h": -2.991001762342671
    },
    {
      "timestamp": "2026-01-12T22:47:02.487778",
      "price": 76.23,
      "change_24h": -3.536861160111484
    },
    {
      "timestamp": "2026-01-12T23:00:03.300079",
      "price": 75.97,
      "change_24h": -3.642063727100125
    },
    {
      "timestamp": "2026-01-12T23:25:24.639829",
      "price": 75.94,
      "change_24h": -4.0717484704047155
    }
  ],
  "solana": [
    {
      "timestamp": "2026-01-12T19:57:01.190312",
      "price": 141.08,
      "change_24h": 1.3460694822454895
    },
    {
      "timestamp": "2026-01-12T20:34:26.323417",
      "price": 140.82,
      "change_24h": 1.992155677459487
    },
    {
      "timestamp": "2026-01-12T20:53:57.532508",
      "price": 140.26,
      "change_24h": 1.5210944761046772
    },
    {
      "timestamp": "2026-01-12T21:25:04.952688",
      "price": 139.78,
      "change_24h": 1.2471266784859814
    },
    {
      "timestamp": "2026-01-12T21:44:27.369961",
      "price": 139.42,
      "change_24h": 0.9803565447049295
    },
    {
      "timestamp": "2026-01-12T21:57:25.838037",
      "price": 138.67,
      "change_24h": 0.1798463185323435
    },
    {
      "timestamp": "2026-01-12T22:28:18.652387",
      "price": 139.42,
      "change_24h": 1.1268937862079693
    },
    {
      "timestamp": "2026-01-12T22:47:02.487778",
      "price": 139.28,
      "change_24h": 0.8123983370051805
    },
    {
      "timestamp": "2026-01-12T23:00:03.300079",
      "price": 139.09,
      "change_24h": 0.6989816944624317
    },
    {
      "timestamp": "2026-01-12T23:25:24.639829",
      "price": 138.66,
      "change_24h": -0.34054707062061856
    }
  ]
}