{
  "bitcoin": [
    {
      "timestamp": "2025-11-16T04:36:04.853671",
      "price": 95635,
      "change_24h": -0.39932073023853065
    },
    {
      "timestamp": "2025-11-16T04:51:26.576873",
      "price": 95746,
      "change_24h": -0.3457225816666051
    },
    {
      "timestamp": "2025-11-16T05:15:38.992051",
      "price": 95964,
      "change_24h": -0.01428337875592226
    },
    {
      "timestamp": "2025-11-16T05:37:21.843086",
      "price": 95877,
      "change_24h": -0.07451245860299945
    },
    {
      "timestamp": "2025-11-16T05:50:20.449315",
      "price": 95895,
      "change_24h": -0.176813563037838
    },
    {
      "timestamp": "2025-11-16T06:20:06.989251",
      "price": 95895,
      "change_24h": -0.47296699930957165
    },
    {
      "timestamp": "2025-11-16T06:46:50.087063",
      "price": 95876,
      "change_24h": -0.17011652514133033
    },
    {
      "timestamp": "2025-11-16T06:59:30.149492",
      "price": 95746,
      "change_24h": -0.48579442704196724
    },
    {
      "timestamp": "2025-11-16T07:25:03.839283",
      "price": 95835,
      "change_24h": -0.21563714813168156
    },
    {
      "timestamp": "2025-11-16T07:39:40.018856",
      "price": 95836,
      "change_24h": -0.35750750654731717
    }
  ],
  "cardano": [
    {
      "timestamp": "2025-11-16T04:36:04.853671",
      "price": 0.501373,
      "change_24h": -1.4965943958215762
    },
    {
      "timestamp": "2025-11-16T04:51:26.576873",
      "price": 0.500327,
      "change_24h": -1.118551819773207
    },
    {
      "timestamp": "2025-11-16T05:15:38.992051",
      "price": 0.503611,
      "change_24h": -0.6851378981592863
    },
    {
      "timestamp": "2025-11-16T05:37:21.843086",
      "price": 0.503422,
      "change_24h": -0.8095228922207903
    },
    {
      "timestamp": "2025-11-16T05:50:20.449315",
      "price": 0.502815,
      "change_24h": -1.0078932353531085
    },
    {
      "timestamp": "2025-11-16T06:20:06.989251",
      "price": 0.503319,
      "change_24h": -1.5426838399449476
    },
    {
      "timestamp": "2025-11-16T06:46:50.087063",
      "price": 0.502877,
      "change_24h": -2.178708071119219
    },
    {
      "timestamp": "2025-11-16T06:59:30.149492",
      "price": 0.502062,
      "change_24h": -2.26017148310415
    },
    {
      "timestamp": "2025-11-16T07:25:03.839283",
      "price": 0.502049,
      "change_24h": -2.1605385539076454
    },
    {
      "timestamp": "2025-11-16T07:39:40.018856",
      "price": 0.503386,
      "change_24h": -1.8542036053160251
    }
  ],
  "ethereum": [
    {
      "timestamp": "2025-11-16T04:36:04.853671",
      "price": 3187.01,
      "change_24h": 0.5834716762849529
    },
    {
      "timestamp": "2025-11-16T04:51:26.576873",
      "price": 3189.72,
      "change_24h": 0.8455915334767978
    },
    {
      "timestamp": "2025-11-16T05:15:38.992051",
      "price": 3205.91,
      "change_24h": 1.4088896616232593
    },
    {
      "timestamp": "2025-11-16T05:37:21.843086",
      "price": 3209.49,
      "change_24h": 1.3125716203459326
    },
    {
      "timestamp": "2025-11-16T05:50:20.449315",
      "price": 3205.54,
      "change_24h": 1.0240174673988574
    },
    {
      "timestamp": "2025-11-16T06:20:06.989251",
      "price": 3209.75,
      "change_24h": 0.9749080371734674
    },
    {
      "timestamp": "2025-11-16T06:46:50.087063",
      "price": 3207.64,
      "change_24h": 1.2056192394132934
    },
    {
      "timestamp": "2025-11-16T06:59:30.149492",
      "price": 3200.98,
      "change_24h": 0.7895485531188364
    },
    {
      "timestamp": "2025-11-16T07:25:03.839283",
      "price": 3202.63,
      "change_24h": 0.7752823563536695
    },
    {
      "timestamp": "2025-11-16T07:39:40.018856",
      "price": 3208.9,
      "change_24h": 0.9908537241881944
    }
  ],
  "litecoin": [
    {
      "timestamp": "2025-11-16T04:36:04.853671",
      "price": 102.38,
      "change_24h": -2.114308976779391
    },
    {
      "timestamp": "2025-11-16T04:51:26.576873",
      "price": 102.17,
      "change_24h": -2.0478860560104852
    },
    {
      "timestamp": "2025-11-16T05:15:38.992051",
      "price": 102.29,
      "change_24h": -1.2445660905640321
    },
    {
      "timestamp": "2025-11-16T05:37:21.843086",
      "price": 102.01,
      "change_24h": -1.0900671445153691
    },
    {
      "timestamp": "2025-11-16T05:50:20.449315",
      "price": 101.94,
      "change_24h": -1.5649252103629059
    },
    {
      "timestamp": "2025-11-16T06:20:06.989251",
      "price": 102.15,
      "change_24h": -1.9281926592768384
    },
    {
      "timestamp": "2025-11-16T06:46:50.087063",
      "price": 102.03,
      "change_24h": -1.8217383832519185
    },
    {
      "timestamp": "2025-11-16T06:59:30.149492",
      "price": 101.72,
      "change_24h": -2.02967610143036
    },
    {
      "timestamp": "2025-11-16T07:25:03.839283",
      "price": 101.59,
      "change_24h": -1.87539337555767
    },
    {
      "timestamp": "2025-11-16T07:39:40.018856",
      "price": 101.81,
      "change_24h": -1.5807484002835066
    }
  ],
  "solana": [
    {
      "timestamp": "2025-11-16T04:36:04.853671",
      "price": 140.91,
      "change_24h": -0.8443281679923151
    },
    {
      "timestamp": "2025-11-16T04:51:26.576873",
      "price": 140.97,
      "change_24h": -0.6485090296822349
    },
    {
      "timestamp": "2025-11-16T05:15:38.992051",
      "price": 141.83,
      "change_24h": -0.4098392223154847
    },
    {
      "timestamp": "2025-11-16T05:37:21.843086",
      "price": 141.47,
      "change_24h": -0.8329662086448028
    },
    {
      "timestamp": "2025-11-16T05:50:20.449315",
      "price": 141.47,
      "change_24h": -0.949797236624598
    },
    {
      "timestamp": "2025-11-16T06:20:06.989251",
      "price": 141.91,
      "change_24h": -0.6671481166420825
    },
    {
      "timestamp": "2025-11-16T06:46:50.087063",
      "price": 141.88,
      "change_24h": -0.42411212569424295
    },
    {
      "timestamp": "2025-11-16T06:59:30.149492",
      "price": 141.83,
      "change_24h": -0.53849132890647
    },
    {
      "timestamp": "2025-11-16T07:25:03.839283",
      "price": 141.49,
      "change_24h": -0.9155533592843998
    },
    {
      "timestamp": "2025-11-16T07:39:40.018856",
      "price": 141.47,
      "change_24h": -1.0181175566314267
    }
  ]
}