{
  "bitcoin": [
    {
      "timestamp": "2026-02-17T12:56:25.998201",
      "price": 68004,
      "change_24h": -2.427113022719944
    },
    {
      "timestamp": "2026-02-17T14:10:02.574958",
      "price": 68165,
      "change_24h": -0.2862276350456217
    },
    {
      "timestamp": "2026-02-17T15:07:27.143343",
      "price": 67023,
      "change_24h": -2.1825171704296675
    },
    {
      "timestamp": "2026-02-17T16:08:07.926261",
      "price": 67836,
      "change_24h": 0.2218726382518023
    },
    {
      "timestamp": "2026-02-17T17:16:44.590743",
      "price": 67213,
      "change_24h": -0.755275692001144
    },
    {
      "timestamp": "2026-02-17T18:09:55.917400",
      "price": 67155,
      "change_24h": -1.34260364205182
    },
    {
      "timestamp": "2026-02-17T19:15:41.759406",
      "price": 68058,
      "change_24h": 0.2008993853511906
    },
    {
      "timestamp": "2026-02-17T19:56:01.276466",
      "price": 67809,
      "change_24h": -0.10725693834236982
    },
    {
      "timestamp": "2026-02-17T20:49:15.056467",
      "price": 67767,
      "change_24h": -0.6230826788943447
    },
    {
      "timestamp": "2026-02-17T21:25:47.177668",
      "price": 67590,
      "change_24h": -1.3569569368897965
    }
  ],
  "cardano": [
    {
      "timestamp": "2026-02-17T12:56:25.998201",
      "price": 0.282123,
      "change_24h": -1.579461279899768
    },
    {
      "timestamp": "2026-02-17T14:10:02.574958",
      "price": 0.28315,
      "change_24h": 0.5543374128691188
    },
    {
      "timestamp": "2026-02-17T15:07:27.143343",
      "price": 0.27839,
      "change_24h": -2.2654209052799748
    },
    {
      "timestamp": "2026-02-17T16:08:07.926261",
      "price": 0.283689,
      "change_24h": 1.1210375859042232
    },
    {
      "timestamp": "2026-02-17T17:16:44.590743",
      "price": 0.281527,
      "change_24h": 0.18836278278554494
    },
    {
      "timestamp": "2026-02-17T18:09:55.917400",
      "price": 0.281174,
      "change_24h": -0.3504830897962826
    },
    {
      "timestamp": "2026-02-17T19:15:41.759406",
      "price": 0.28492,
      "change_24h": 1.117486287248492
    },
    {
      "timestamp": "2026-02-17T19:56:01.276466",
      "price": 0.283256,
      "change_24h": 0.22704457868189856
    },
    {
      "timestamp": "2026-02-17T20:49:15.056467",
      "price": 0.282683,
      "change_24h": -0.3423445124022821
    },
    {
      "timestamp": "2026-02-17T21:25:47.177668",
      "price": 0.282619,
      "change_24h": -1.0163601960523814
    }
  ],
  "ethereum": [
    {
      "timestamp": "2026-02-17T12:56:25.998201",
      "price": 1970.57,
      "change_24h": -1.714499793466644
    },
    {
      "timestamp": "2026-02-17T14:10:02.574958",
      "price": 1995.73,
      "change_24h": 1.3186895036456214
    },
    {
      "timestamp": "2026-02-17T15:07:27.143343",
      "price": 1950.65,
      "change_24h": -1.564617319038158
    },
    {
      "timestamp": "2026-02-17T16:08:07.926261",
      "price": 1990.65,
      "change_24h": 1.0420235676877199
    },
    {
      "timestamp": "2026-02-17T17:16:44.590743",
      "price": 1963.75,
      "change_24h": -0.3955653606406791
    },
    {
      "timestamp": "2026-02-17T18:09:55.917400",
      "price": 1963.04,
      "change_24h": -0.9277887759117621
    },
    {
      "timestamp": "2026-02-17T19:15:41.759406",
      "price": 2009.11,
      "change_24h": 1.9937342899275758
    },
    {
      "timestamp": "2026-02-17T19:56:01.276466",
      "price": 1999.54,
      "change_24h": 1.3318639240739265
    },
    {
      "timestamp": "2026-02-17T20:49:15.056467",
      "price": 1995.59,
      "change_24h": 0.6526723587540076
    },
    {
      "timestamp": "2026-02-17T21:25:47.177668",
      "price": 1993.53,
      "change_24h": 0.21834522431324932
    }
  ],
  "litecoin": [
    {
      "timestamp": "2026-02-17T12:56:25.998201",
      "price": 54.87,
      "change_24h": 0.6306300287006996
    },
    {
      "timestamp": "2026-02-17T14:10:02.574958",
      "price": 55.0,
      "change_24h": 1.862102039985697
    },
    {
      "timestamp": "2026-02-17T15:07:27.143343",
      "price": 54.01,
      "change_24h": -0.6765631971553646
    },
    {
      "timestamp": "2026-02-17T16:08:07.926261",
      "price": 54.09,
      "change_24h": 0.8473096325947258
    },
    {
      "timestamp": "2026-02-17T17:16:44.590743",
      "price": 54.14,
      "change_24h": 0.9322464647580366
    },
    {
      "timestamp": "2026-02-17T18:09:55.917400",
      "price": 53.89,
      "change_24h": -0.015174742407772062
    },
    {
      "timestamp": "2026-02-17T19:15:41.759406",
      "price": 54.55,
      "change_24h": 1.1360795707806952
    },
    {
      "timestamp": "2026-02-17T19:56:01.276466",
      "price": 54.25,
      "change_24h": -0.033743054226480614
    },
    {
      "timestamp": "2026-02-17T20:49:15.056467",
      "price": 54.18,
      "change_24h": -1.0314529590791401
    },
    {
      "timestamp": "2026-02-17T21:25:47.177668",
      "price": 54.34,
      "change_24h": -1.2704833980802999
    }
  ],
  "solana": [
    {
      "timestamp": "2026-02-17T12:56:25.998201",
      "price": 84.83,
      "change_24h": -1.5185565468631435
    },
    {
      "timestamp": "2026-02-17T14:10:02.574958",
      "price": 85.11,
      "change_24h": 1.1760687115135988
    },
    {
      "timestamp": "2026-02-17T15:07:27.143343",
      "price": 83.33,
      "change_24h": -1.2144404444441697
    },
    {
      "timestamp": "2026-02-17T16:08:07.926261",
      "price": 84.36,
      "change_24h": 1.0140743946547963
    },
    {
      "timestamp": "2026-02-17T17:16:44.590743",
      "price": 83.76,
      "change_24h": -0.4296956808249798
    },
    {
      "timestamp": "2026-02-17T18:09:55.917400",
      "price": 83.67,
      "change_24h": -1.0229238808627397
    },
    {
      "timestamp": "2026-02-17T19:15:41.759406",
      "price": 85.25,
      "change_24h": 0.8624724255493951
    },
    {
      "timestamp": "2026-02-17T19:56:01.276466",
      "price": 84.81,
      "change_24h": 0.12737690803494972
    },
    {
      "timestamp": "2026-02-17T20:49:15.056467",
      "price": 85.03,
      "change_24h": -0.06615311095402407
    },
    {
      "timestamp": "2026-02-17T21:25:47.177668",
      "price": 85.15,
      "change_24h": -0.3638047114944893
    }
  ]
}