{
  "bitcoin": [
    {
      "timestamp": "2025-10-26T23:24:34.797951",
      "price": 114522,
      "change_24h": 2.6360629324225804
    },
    {
      "timestamp": "2025-10-26T23:39:58.504751",
      "price": 114652,
      "change_24h": 2.7321735340883913
    },
    {
      "timestamp": "2025-10-26T23:52:53.053098",
      "price": 114551,
      "change_24h": 2.6253973264499946
    },
    {
      "timestamp": "2025-10-27T01:42:38.357643",
      "price": 115270,
      "change_24h": 3.1367071086839373
    },
    {
      "timestamp": "2025-10-27T03:10:50.269746",
      "price": 114953,
      "change_24h": 3.132952241885768
    },
    {
      "timestamp": "2025-10-27T03:59:42.078780",
      "price": 114969,
      "change_24h": 3.317000384614706
    },
    {
      "timestamp": "2025-10-27T04:37:46.085595",
      "price": 115194,
      "change_24h": 3.351420584104456
    },
    {
      "timestamp": "2025-10-27T04:55:22.262265",
      "price": 115248,
      "change_24h": 3.4043469175506074
    },
    {
      "timestamp": "2025-10-27T05:27:03.525351",
      "price": 115473,
      "change_24h": 3.5641707304832018
    },
    {
      "timestamp": "2025-10-27T05:45:14.251728",
      "price": 115622,
      "change_24h": 3.571804224784314
    }
  ],
  "cardano": [
    {
      "timestamp": "2025-10-26T23:24:34.797951",
      "price": 0.683923,
      "change_24h": 4.421380010723238
    },
    {
      "timestamp": "2025-10-26T23:39:58.504751",
      "price": 0.684458,
      "change_24h": 4.560321698960725
    },
    {
      "timestamp": "2025-10-26T23:52:53.053098",
      "price": 0.682965,
      "change_24h": 4.2977301650502815
    },
    {
      "timestamp": "2025-10-27T01:42:38.357643",
      "price": 0.688798,
      "change_24h": 5.467633928902237
    },
    {
      "timestamp": "2025-10-27T03:10:50.269746",
      "price": 0.688743,
      "change_24h": 6.170584018095564
    },
    {
      "timestamp": "2025-10-27T03:59:42.078780",
      "price": 0.684213,
      "change_24h": 5.627817450746984
    },
    {
      "timestamp": "2025-10-27T04:37:46.085595",
      "price": 0.682705,
      "change_24h": 4.958762634737762
    },
    {
      "timestamp": "2025-10-27T04:55:22.262265",
      "price": 0.683566,
      "change_24h": 5.054901847570636
    },
    {
      "timestamp": "2025-10-27T05:27:03.525351",
      "price": 0.689059,
      "change_24h": 5.9708639517018325
    },
    {
      "timestamp": "2025-10-27T05:45:14.251728",
      "price": 0.687297,
      "change_24h": 5.228948987638767
    }
  ],
  "ethereum": [
    {
      "timestamp": "2025-10-26T23:24:34.797951",
      "price": 4170.34,
      "change_24h": 5.4238986341338125
    },
    {
      "timestamp": "2025-10-26T23:39:58.504751",
      "price": 4172.23,
      "change_24h": 5.471017582192202
    },
    {
      "timestamp": "2025-10-26T23:52:53.053098",
      "price": 4167.79,
      "change_24h": 5.404813267676496
    },
    {
      "timestamp": "2025-10-27T01:42:38.357643",
      "price": 4199.36,
      "change_24h": 6.22905312585592
    },
    {
      "timestamp": "2025-10-27T03:10:50.269746",
      "price": 4209.9,
      "change_24h": 7.220328539602111
    },
    {
      "timestamp": "2025-10-27T03:59:42.078780",
      "price": 4205.27,
      "change_24h": 6.980878316247613
    },
    {
      "timestamp": "2025-10-27T04:37:46.085595",
      "price": 4197.68,
      "change_24h": 6.687166283935546
    },
    {
      "timestamp": "2025-10-27T04:55:22.262265",
      "price": 4214.81,
      "change_24h": 6.997571170761339
    },
    {
      "timestamp": "2025-10-27T05:27:03.525351",
      "price": 4246.04,
      "change_24h": 7.725300656808172
    },
    {
      "timestamp": "2025-10-27T05:45:14.251728",
      "price": 4232.52,
      "change_24h": 7.262281391409858
    }
  ],
  "litecoin": [
    {
      "timestamp": "2025-10-26T23:24:34.797951",
      "price": 100.09,
      "change_24h": 3.4334406153719166
    },
    {
      "timestamp": "2025-10-26T23:39:58.504751",
      "price": 100.0,
      "change_24h": 3.1330277179849273
    },
    {
      "timestamp": "2025-10-26T23:52:53.053098",
      "price": 100.0,
      "change_24h": 3.137933796460992
    },
    {
      "timestamp": "2025-10-27T01:42:38.357643",
      "price": 100.55,
      "change_24h": 3.749633344751696
    },
    {
      "timestamp": "2025-10-27T03:10:50.269746",
      "price": 100.34,
      "change_24h": 3.959644212640627
    },
    {
      "timestamp": "2025-10-27T03:59:42.078780",
      "price": 99.99,
      "change_24h": 3.6485015788748596
    },
    {
      "timestamp": "2025-10-27T04:37:46.085595",
      "price": 100.18,
      "change_24h": 3.786320655412202
    },
    {
      "timestamp": "2025-10-27T04:55:22.262265",
      "price": 100.48,
      "change_24h": 3.9675851121618395
    },
    {
      "timestamp": "2025-10-27T05:27:03.525351",
      "price": 100.78,
      "change_24h": 4.196092581801097
    },
    {
      "timestamp": "2025-10-27T05:45:14.251728",
      "price": 100.71,
      "change_24h": 4.02306250965039
    }
  ],
  "solana": [
    {
      "timestamp": "2025-10-26T23:24:34.797951",
      "price": 200.13,
      "change_24h": 3.017622803013285
    },
    {
      "timestamp": "2025-10-26T23:39:58.504751",
      "price": 200.63,
      "change_24h": 3.3157800940121684
    },
    {
      "timestamp": "2025-10-26T23:52:53.053098",
      "price": 200.22,
      "change_24h": 3.1399735465926693
    },
    {
      "timestamp": "2025-10-27T01:42:38.357643",
      "price": 204.62,
      "change_24h": 5.696036418878333
    },
    {
      "timestamp": "2025-10-27T03:10:50.269746",
      "price": 204.11,
      "change_24h": 6.109634638093712
    },
    {
      "timestamp": "2025-10-27T03:59:42.078780",
      "price": 204.24,
      "change_24h": 5.813056994165936
    },
    {
      "timestamp": "2025-10-27T04:37:46.085595",
      "price": 203.52,
      "change_24h": 5.3376789024856
    },
    {
      "timestamp": "2025-10-27T04:55:22.262265",
      "price": 203.84,
      "change_24h": 5.475603211573209
    },
    {
      "timestamp": "2025-10-27T05:27:03.525351",
      "price": 204.94,
      "change_24h": 6.08101904294237
    },
    {
      "timestamp": "2025-10-27T05:45:14.251728",
      "price": 204.8,
      "change_24h": 5.781958524620965
    }
  ]
}